etc/bash_completion.d/ytmdl.bash
usr/share/zsh/functions/Completion/Unix/ytmdl.zsh
ytmdl/__init__.py
ytmdl/__version__.py
ytmdl/cache.py
ytmdl/core.py
ytmdl/defaults.py
ytmdl/dir.py
ytmdl/exceptions.py
ytmdl/main.py
ytmdl/manual.py
ytmdl/metadata.py
ytmdl/prepend.py
ytmdl/setupConfig.py
ytmdl/song.py
ytmdl/stringutils.py
ytmdl/trim.py
ytmdl/utility.py
ytmdl/yt.py
ytmdl/meta/__init__.py
ytmdl/meta/deezer.py
ytmdl/meta/gaana.py
ytmdl/meta/lastfm.py
ytmdl/meta/musicbrainz.py
ytmdl/meta/preconfig.py
ytmdl/meta/saavn.py
ytmdl/meta/spotify.py
ytmdl/meta/yt.py
ytmdl/utils/__init__.py
ytmdl/utils/archive.py
ytmdl/utils/ytdl.py
ytmdl/utils/ytmusic.py
ytmdl-2024.8.15.1.dist-info/LICENSE
ytmdl-2024.8.15.1.dist-info/METADATA
ytmdl-2024.8.15.1.dist-info/WHEEL
ytmdl-2024.8.15.1.dist-info/entry_points.txt
ytmdl-2024.8.15.1.dist-info/top_level.txt
ytmdl-2024.8.15.1.dist-info/RECORD
