Metadata-Version: 2.1
Name: ytmdl
Version: 2024.8.15.1
Summary: Youtube Music Downloader
Home-page: https://github.com/deepjyoti30/ytmdl
Author: Deepjyoti Barman
Author-email: deep.barma30@gmail.com
Classifier: Programming Language :: Python :: 3
Classifier: License :: OSI Approved :: MIT License
Classifier: Operating System :: OS Independent
Classifier: Development Status :: 5 - Production/Stable
Classifier: Environment :: Console
Classifier: Topic :: Multimedia :: Sound/Audio
Requires-Python: >=3.6.2
License-File: LICENSE
Requires-Dist: yt-dlp>=2024.4.9
Requires-Dist: mutagen
Requires-Dist: itunespy
Requires-Dist: requests
Requires-Dist: colorama
Requires-Dist: beautifulsoup4
Requires-Dist: downloader-cli>=0.3.4
Requires-Dist: pyxdg
Requires-Dist: ffmpeg-python
Requires-Dist: pysocks
Requires-Dist: unidecode
Requires-Dist: youtube-search-python
Requires-Dist: pyDes
Requires-Dist: urllib3
Requires-Dist: simber==0.2.6
Requires-Dist: rich
Requires-Dist: musicbrainzngs
Requires-Dist: ytmusicapi
Requires-Dist: spotipy
Provides-Extra: noise-clean
Requires-Dist: inaSpeechSegmenter; extra == "noise-clean"
Requires-Dist: tensorflow; extra == "noise-clean"
